bgtools/Dice.py
bgtools/Table.py
bgtools/__init__.py
bgtools-0.0.1.dist-info/DESCRIPTION.rst
bgtools-0.0.1.dist-info/LICENSE.txt
bgtools-0.0.1.dist-info/METADATA
bgtools-0.0.1.dist-info/RECORD
bgtools-0.0.1.dist-info/WHEEL
bgtools-0.0.1.dist-info/metadata.json
bgtools-0.0.1.dist-info/top_level.txt
