Metadata-Version: 2.0
Name: bgtools
Version: 0.0.1
Summary: bgtools: A Python package for managing playing board games
Home-page: https://github.com/niemasd/bgtools
Author: Niema Moshiri
Author-email: niemamoshiri@gmail.com
License: UNKNOWN
Project-URL: Source, https://github.com/niemasd/bgtools
Project-URL: Bug Reports, https://github.com/niemasd/bgtools/issues
Keywords: tree phylogenetics fast
Platform: UNKNOWN
Classifier: Development Status :: 3 - Alpha
Classifier: Intended Audience :: Developers
Classifier: Topic :: Software Development :: Build Tools
Classifier: License :: OSI Approved :: GNU General Public License v3 or later (GPLv3+)
Classifier: Programming Language :: Python :: 2
Classifier: Programming Language :: Python :: 2.7
Classifier: Programming Language :: Python :: 3
Classifier: Programming Language :: Python :: 3.4
Classifier: Programming Language :: Python :: 3.5
Classifier: Programming Language :: Python :: 3.6
Provides-Extra: dev
Provides-Extra: dev
Requires-Dist: check-manifest; extra == 'dev'
